Workbook

Sheet How_To
A1: RENOVIT Economic Simulation Model
A2: Purpose | B2: Compare used vs hybrid vs new equipment across 3k 5k 10k 20k t/year capacity scenarios.
A3: How to use | B3: Edit Inputs and Equipment_Costs. Scenario_Matrix recalculates formulas when opened in Excel or compatible spreadsheet.
A4: Canonical product | B4: Tencuiala gipsata ambalata in sac 25kg.
A5: No tax layer | B5: VAT and corporate tax are intentionally excluded from this feasibility cockpit.
A6: Optional financing | B6: Set financing_enabled to 1 or 0 in Inputs. Debt service affects cash after debt but not operating EBITDA.
A7: Source folder | B7: data/finance/simulation/

Sheet Inputs
A1: Category | B1: Key | C1: Label | D1: Value | E1: Unit | F1: Notes
A2: Product | B2: target_bag_kg | C2: Target bag size | D2: 25 | E2: kg | F2: Canonical RENOVIT packaging decision
A3: Product | B3: bags_per_pallet | C3: Bags per pallet | D3: 48 | E3: bags | F3: Working logistics assumption
A4: Revenue | B4: selling_price_eur_per_ton | C4: Wholesale selling price | D4: 120 | E4: EUR/t | F4: Equivalent to 3 EUR per 25kg bag
A5: Production | B5: process_yield | C5: Raw to finished yield | D5: 0.75 | E5: ratio | F5: Raw gypsum to finished packaged product
A6: Raw material | B6: extraction_cost_eur_per_raw_t | C6: Extraction cost | D6: 8 | E6: EUR/raw t | F6: Partner data needed
A7: Raw material | B7: quarry_to_plant_transport_eur_per_raw_t | C7: Quarry to plant transport | D7: 4 | E7: EUR/raw t | F7: Depends on plant location
A8: Processing | B8: calcination_eur_per_finished_t | C8: Calcination cost | D8: 15 | E8: EUR/t | F8: Energy and kiln operation
A9: Processing | B9: grinding_eur_per_finished_t | C9: Grinding cost | D9: 8 | E9: EUR/t | F9: Fine grinding to target fineness
A10: Processing | B10: additives_eur_per_finished_t | C10: Additives cost | D10: 8 | E10: EUR/t | F10: Retarder and product performance additives
A11: Processing | B11: direct_labor_eur_per_finished_t | C11: Direct labor | D11: 7 | E11: EUR/t | F11: Production labor
A12: Packaging | B12: bag_packaging_eur_per_bag | C12: Bag and label cost | D12: 0.15 | E12: EUR/bag | F12: 25kg bag and labeling
A13: Logistics | B13: distribution_eur_per_finished_t | C13: Distribution cost | D13: 6 | E13: EUR/t | F13: Finished goods local logistics
... A20: Financing | B20: loan_term_years | C20: Loan term | D20: 5 | E20: years | F20: Optional debt term

Sheet Capacity_Phases
A1: Scenario | B1: Phase | C1: Capacity t/year | D1: Capacity t/month | E1: Default utilization | F1: Canonical verdict | G1: Key gate | H1: Notes
A2: Pilot | B2: Phase 0/1 | C2: 3000 | D2: 250 | E2: 0.6 | F2: Risk | G2: Market validation only | H2: Small pilot can reduce risk but may underuse fixed costs
A3: Start optimal | B3: Phase 1 | C3: 5000 | D3: 417 | E3: 0.7 | F3: START OPTIMAL | G3: Quality plus buyer validation | H3: Default industrial starting point
A4: Scale-up | B4: Phase 2 | C4: 10000 | D4: 833 | E4: 0.75 | F4: Scalable | G4: Demand above phase 1 capacity | H4: Add modules after stable production
A5: Industrial | B5: Phase 3 | C5: 20000 | D5: 1667 | E5: 0.8 | F5: Industrial | G5: Financing plus distribution capacity | H5: Requires stronger team and market access

Sheet Equipment_Costs
A1: Strategy | B1: Item | C1: Cost EUR 5k base | D1: Phase | E1: Notes
A2: used | B2: Calcination caldron or drum | C2: 90000 | D2: Phase 1 | E2: Used or refurbished core kiln
A3: used | B3: Grinding and mixer package | C3: 40000 | D3: Phase 1 | E3: Used package or separate machines
A4: used | B4: 25kg bagging line | C4: 30000 | D4: Phase 1 | E4: Used bag filling sealing and printing
A5: used | B5: Silo and internal logistics | C5: 22500 | D5: Phase 1 | E5: Used or local fabrication
A6: used | B6: Jaw crusher | C6: 25000 | D6: Phase 1 | E6: Only if feed size requires crushing
A7: used | B7: Dust collection and filters | C7: 25000 | D7: Phase 1 | E7: Do not ignore environment and worker safety
A8: used | B8: Electrical works | C8: 30000 | D8: Phase 1 | E8: Power connection and panels
A9: used | B9: Gas or fuel system | C9: 20000 | D9: Phase 1 | E9: Burner connection or fuel system
A10: used | B10: Forklift and warehouse handling | C10: 12000 | D10: Phase 1 | E10: Used forklift and simple handling
A11: used | B11: Minimum quality lab | C11: 10000 | D11: Phase 1 | E11: Vicat balance sieves press baseline
A12: used | B12: Installation and commissioning | C12: 25000 | D12: Phase 1 | E12: Assembly commissioning and technician work
A13: hybrid | B13: Calcination caldron or drum | C13: 120000 | D13: Phase 1 | E13: Refurbished core with stronger inspection
... A34: new | B34: Installation and commissioning | C34: 60000 | D34: Phase 1 | E34: Supplier commissioning

Sheet Strategy_Rates
A1: Strategy | B1: Repair reserve % | C1: Contingency % | D1: Scale exponent | E1: Maintenance % annual | F1: Lead time months | G1: Notes
A2: used | B2: 0.2 | C2: 0.12 | D2: 0.85 | E2: 0.06 | F2: 1.5 | G2: Lowest CAPEX but highest commissioning and downtime risk
A3: hybrid | B3: 0.1 | C3: 0.12 | D3: 0.78 | E3: 0.04 | F3: 3 | G3: Balanced option for safety-critical new components
A4: new | B4: 0 | C4: 0.1 | D4: 0.72 | E4: 0.03 | F4: 4 | G4: Higher CAPEX but better uptime and scale logic

Sheet Scenario_Matrix
A1: Scenario ID | B1: Capacity scenario | C1: Capacity t/year | D1: Strategy | E1: Utilization % | F1: Finished t/year | G1: Finished t/month | H1: Bags/month | I1: Price EUR/t | J1: Price EUR/bag | K1: Base equipment CAPEX 5k | L1: Repair reserve | M1: Contingency | N1: Base CAPEX 5k complete | O1: Scale factor | P1: Scaled CAPEX | Q1: Raw cost/t | R1: Packaging cost/t | S1: Variable cost/t | T1: Fixed + maintenance/month | U1: Working capital | V1: Total funding need | W1: Revenue/month | X1: Gross profit/month | Y1: EBITDA/month | Z1: Gross margin % | AA1: Break-even t/month | AB1: Break-even bags/month | AC1: Break-even revenue/month | AD1: Payback years | AE1: ROI 3y | AF1: Debt/month | AG1: Cash after debt/month | AH1: DSCR | AI1: Verdict
A2: pilot_used | B2: Pilot | C2: 3000 | D2: used | E2: 0.6 | F2: =C2*E2 -> 0 | G2: =F2/12 -> 0 | H2: =G2*1000/Inputs!$D$2 -> 0 | I2: =Inputs!$D$4 -> 0 | J2: =I2/(1000/Inputs!$D$2) -> 0 | K2: =SUMIF(Equipment_Costs!$A:$A,D2,Equipment_Costs!$C:$C) -> 0 | L2: =K2*VLOOKUP(D2,Strategy_Rates!$A:$G,2,FALSE) -> 0 | M2: =(K2+L2)*VLOOKUP(D2,Strategy_Rates!$A:$G,3,FALSE) -> 0 | N2: =K2+L2+M2 -> 0 | O2: =(C2/5000)^VLOOKUP(D2,Strategy_Rates!$A:$G,4,FALSE) -> 0 | P2: =N2*O2 -> 0 | Q2: =(Inputs!$D$6+Inputs!$D$7)/Inputs!$D$5 -> 0 | R2: =Inputs!$D$12*(1000/Inputs!$D$2) -> 0 | S2: =Q2+Inputs!$D$8+Inputs!$D$9+Inputs!$D$10+Inputs!$D$11+R2+Inputs!$D$13+Inputs!$D$14 -> 0 | T2: =Inputs!$D$15+P2*VLOOKUP(D2,Strategy_Rates!$A:$G,5,FALSE)/12 -> 0 | U2: =Inputs!$D$16*(S2*G2+T2) -> 0 | V2: =P2+U2 -> 0 | W2: =I2*G2 -> 0 | X2: =(I2-S2)*G2 -> 0 | Y2: =W2-S2*G2-T2 -> 0 | Z2: =IF(I2>0,(I2-S2)/I2,0) -> 0 | AA2: =IF(I2>S2,T2/(I2-S2),0) -> 0 | AB2: =AA2*1000/Inputs!$D$2 -> 0 | AC2: =AA2*I2 -> 0 | AD2: =IF(Y2>0,V2/(Y2*12),999) -> 0 | AE2: =IF(V2>0,(Y2*36-V2)/V2,0) -> 0 | AF2: =IF(Inputs!$D$17=1,IF(Inputs!$D$19>0,V2*Inputs!$D$18*Inputs!$D$19/(1-(1+Inputs!$D$19)^(-Inputs!$D$20))/12,V2*Inputs!$D$18/Inputs!$D$20/12),0) -> 0 | AG2: =Y2-AF2 -> 0 | AH2: =IF(AF2>0,Y2/AF2,0) -> 0 | AI2: =IF(AND(Z2>=0.35,AD2<=3.5,Y2>0),"GO",IF(AND(Z2>=0.25,Y2>0),"GO conditional",IF(Y2>0,"Risk","NO-GO"))) -> 0
A3: pilot_hybrid | B3: Pilot | C3: 3000 | D3: hybrid | E3: 0.6 | F3: =C3*E3 -> 0 | G3: =F3/12 -> 0 | H3: =G3*1000/Inputs!$D$2 -> 0 | I3: =Inputs!$D$4 -> 0 | J3: =I3/(1000/Inputs!$D$2) -> 0 | K3: =SUMIF(Equipment_Costs!$A:$A,D3,Equipment_Costs!$C:$C) -> 0 | L3: =K3*VLOOKUP(D3,Strategy_Rates!$A:$G,2,FALSE) -> 0 | M3: =(K3+L3)*VLOOKUP(D3,Strategy_Rates!$A:$G,3,FALSE) -> 0 | N3: =K3+L3+M3 -> 0 | O3: =(C3/5000)^VLOOKUP(D3,Strategy_Rates!$A:$G,4,FALSE) -> 0 | P3: =N3*O3 -> 0 | Q3: =(Inputs!$D$6+Inputs!$D$7)/Inputs!$D$5 -> 0 | R3: =Inputs!$D$12*(1000/Inputs!$D$2) -> 0 | S3: =Q3+Inputs!$D$8+Inputs!$D$9+Inputs!$D$10+Inputs!$D$11+R3+Inputs!$D$13+Inputs!$D$14 -> 0 | T3: =Inputs!$D$15+P3*VLOOKUP(D3,Strategy_Rates!$A:$G,5,FALSE)/12 -> 0 | U3: =Inputs!$D$16*(S3*G3+T3) -> 0 | V3: =P3+U3 -> 0 | W3: =I3*G3 -> 0 | X3: =(I3-S3)*G3 -> 0 | Y3: =W3-S3*G3-T3 -> 0 | Z3: =IF(I3>0,(I3-S3)/I3,0) -> 0 | AA3: =IF(I3>S3,T3/(I3-S3),0) -> 0 | AB3: =AA3*1000/Inputs!$D$2 -> 0 | AC3: =AA3*I3 -> 0 | AD3: =IF(Y3>0,V3/(Y3*12),999) -> 0 | AE3: =IF(V3>0,(Y3*36-V3)/V3,0) -> 0 | AF3: =IF(Inputs!$D$17=1,IF(Inputs!$D$19>0,V3*Inputs!$D$18*Inputs!$D$19/(1-(1+Inputs!$D$19)^(-Inputs!$D$20))/12,V3*Inputs!$D$18/Inputs!$D$20/12),0) -> 0 | AG3: =Y3-AF3 -> 0 | AH3: =IF(AF3>0,Y3/AF3,0) -> 0 | AI3: =IF(AND(Z3>=0.35,AD3<=3.5,Y3>0),"GO",IF(AND(Z3>=0.25,Y3>0),"GO conditional",IF(Y3>0,"Risk","NO-GO"))) -> 0
A4: pilot_new | B4: Pilot | C4: 3000 | D4: new | E4: 0.6 | F4: =C4*E4 -> 0 | G4: =F4/12 -> 0 | H4: =G4*1000/Inputs!$D$2 -> 0 | I4: =Inputs!$D$4 -> 0 | J4: =I4/(1000/Inputs!$D$2) -> 0 | K4: =SUMIF(Equipment_Costs!$A:$A,D4,Equipment_Costs!$C:$C) -> 0 | L4: =K4*VLOOKUP(D4,Strategy_Rates!$A:$G,2,FALSE) -> 0 | M4: =(K4+L4)*VLOOKUP(D4,Strategy_Rates!$A:$G,3,FALSE) -> 0 | N4: =K4+L4+M4 -> 0 | O4: =(C4/5000)^VLOOKUP(D4,Strategy_Rates!$A:$G,4,FALSE) -> 0 | P4: =N4*O4 -> 0 | Q4: =(Inputs!$D$6+Inputs!$D$7)/Inputs!$D$5 -> 0 | R4: =Inputs!$D$12*(1000/Inputs!$D$2) -> 0 | S4: =Q4+Inputs!$D$8+Inputs!$D$9+Inputs!$D$10+Inputs!$D$11+R4+Inputs!$D$13+Inputs!$D$14 -> 0 | T4: =Inputs!$D$15+P4*VLOOKUP(D4,Strategy_Rates!$A:$G,5,FALSE)/12 -> 0 | U4: =Inputs!$D$16*(S4*G4+T4) -> 0 | V4: =P4+U4 -> 0 | W4: =I4*G4 -> 0 | X4: =(I4-S4)*G4 -> 0 | Y4: =W4-S4*G4-T4 -> 0 | Z4: =IF(I4>0,(I4-S4)/I4,0) -> 0 | AA4: =IF(I4>S4,T4/(I4-S4),0) -> 0 | AB4: =AA4*1000/Inputs!$D$2 -> 0 | AC4: =AA4*I4 -> 0 | AD4: =IF(Y4>0,V4/(Y4*12),999) -> 0 | AE4: =IF(V4>0,(Y4*36-V4)/V4,0) -> 0 | AF4: =IF(Inputs!$D$17=1,IF(Inputs!$D$19>0,V4*Inputs!$D$18*Inputs!$D$19/(1-(1+Inputs!$D$19)^(-Inputs!$D$20))/12,V4*Inputs!$D$18/Inputs!$D$20/12),0) -> 0 | AG4: =Y4-AF4 -> 0 | AH4: =IF(AF4>0,Y4/AF4,0) -> 0 | AI4: =IF(AND(Z4>=0.35,AD4<=3.5,Y4>0),"GO",IF(AND(Z4>=0.25,Y4>0),"GO conditional",IF(Y4>0,"Risk","NO-GO"))) -> 0
A5: start_used | B5: Start optimal | C5: 5000 | D5: used | E5: 0.7 | F5: =C5*E5 -> 0 | G5: =F5/12 -> 0 | H5: =G5*1000/Inputs!$D$2 -> 0 | I5: =Inputs!$D$4 -> 0 | J5: =I5/(1000/Inputs!$D$2) -> 0 | K5: =SUMIF(Equipment_Costs!$A:$A,D5,Equipment_Costs!$C:$C) -> 0 | L5: =K5*VLOOKUP(D5,Strategy_Rates!$A:$G,2,FALSE) -> 0 | M5: =(K5+L5)*VLOOKUP(D5,Strategy_Rates!$A:$G,3,FALSE) -> 0 | N5: =K5+L5+M5 -> 0 | O5: =(C5/5000)^VLOOKUP(D5,Strategy_Rates!$A:$G,4,FALSE) -> 0 | P5: =N5*O5 -> 0 | Q5: =(Inputs!$D$6+Inputs!$D$7)/Inputs!$D$5 -> 0 | R5: =Inputs!$D$12*(1000/Inputs!$D$2) -> 0 | S5: =Q5+Inputs!$D$8+Inputs!$D$9+Inputs!$D$10+Inputs!$D$11+R5+Inputs!$D$13+Inputs!$D$14 -> 0 | T5: =Inputs!$D$15+P5*VLOOKUP(D5,Strategy_Rates!$A:$G,5,FALSE)/12 -> 0 | U5: =Inputs!$D$16*(S5*G5+T5) -> 0 | V5: =P5+U5 -> 0 | W5: =I5*G5 -> 0 | X5: =(I5-S5)*G5 -> 0 | Y5: =W5-S5*G5-T5 -> 0 | Z5: =IF(I5>0,(I5-S5)/I5,0) -> 0 | AA5: =IF(I5>S5,T5/(I5-S5),0) -> 0 | AB5: =AA5*1000/Inputs!$D$2 -> 0 | AC5: =AA5*I5 -> 0 | AD5: =IF(Y5>0,V5/(Y5*12),999) -> 0 | AE5: =IF(V5>0,(Y5*36-V5)/V5,0) -> 0 | AF5: =IF(Inputs!$D$17=1,IF(Inputs!$D$19>0,V5*Inputs!$D$18*Inputs!$D$19/(1-(1+Inputs!$D$19)^(-Inputs!$D$20))/12,V5*Inputs!$D$18/Inputs!$D$20/12),0) -> 0 | AG5: =Y5-AF5 -> 0 | AH5: =IF(AF5>0,Y5/AF5,0) -> 0 | AI5: =IF(AND(Z5>=0.35,AD5<=3.5,Y5>0),"GO",IF(AND(Z5>=0.25,Y5>0),"GO conditional",IF(Y5>0,"Risk","NO-GO"))) -> 0
A6: start_hybrid | B6: Start optimal | C6: 5000 | D6: hybrid | E6: 0.7 | F6: =C6*E6 -> 0 | G6: =F6/12 -> 0 | H6: =G6*1000/Inputs!$D$2 -> 0 | I6: =Inputs!$D$4 -> 0 | J6: =I6/(1000/Inputs!$D$2) -> 0 | K6: =SUMIF(Equipment_Costs!$A:$A,D6,Equipment_Costs!$C:$C) -> 0 | L6: =K6*VLOOKUP(D6,Strategy_Rates!$A:$G,2,FALSE) -> 0 | M6: =(K6+L6)*VLOOKUP(D6,Strategy_Rates!$A:$G,3,FALSE) -> 0 | N6: =K6+L6+M6 -> 0 | O6: =(C6/5000)^VLOOKUP(D6,Strategy_Rates!$A:$G,4,FALSE) -> 0 | P6: =N6*O6 -> 0 | Q6: =(Inputs!$D$6+Inputs!$D$7)/Inputs!$D$5 -> 0 | R6: =Inputs!$D$12*(1000/Inputs!$D$2) -> 0 | S6: =Q6+Inputs!$D$8+Inputs!$D$9+Inputs!$D$10+Inputs!$D$11+R6+Inputs!$D$13+Inputs!$D$14 -> 0 | T6: =Inputs!$D$15+P6*VLOOKUP(D6,Strategy_Rates!$A:$G,5,FALSE)/12 -> 0 | U6: =Inputs!$D$16*(S6*G6+T6) -> 0 | V6: =P6+U6 -> 0 | W6: =I6*G6 -> 0 | X6: =(I6-S6)*G6 -> 0 | Y6: =W6-S6*G6-T6 -> 0 | Z6: =IF(I6>0,(I6-S6)/I6,0) -> 0 | AA6: =IF(I6>S6,T6/(I6-S6),0) -> 0 | AB6: =AA6*1000/Inputs!$D$2 -> 0 | AC6: =AA6*I6 -> 0 | AD6: =IF(Y6>0,V6/(Y6*12),999) -> 0 | AE6: =IF(V6>0,(Y6*36-V6)/V6,0) -> 0 | AF6: =IF(Inputs!$D$17=1,IF(Inputs!$D$19>0,V6*Inputs!$D$18*Inputs!$D$19/(1-(1+Inputs!$D$19)^(-Inputs!$D$20))/12,V6*Inputs!$D$18/Inputs!$D$20/12),0) -> 0 | AG6: =Y6-AF6 -> 0 | AH6: =IF(AF6>0,Y6/AF6,0) -> 0 | AI6: =IF(AND(Z6>=0.35,AD6<=3.5,Y6>0),"GO",IF(AND(Z6>=0.25,Y6>0),"GO conditional",IF(Y6>0,"Risk","NO-GO"))) -> 0
A7: start_new | B7: Start optimal | C7: 5000 | D7: new | E7: 0.7 | F7: =C7*E7 -> 0 | G7: =F7/12 -> 0 | H7: =G7*1000/Inputs!$D$2 -> 0 | I7: =Inputs!$D$4 -> 0 | J7: =I7/(1000/Inputs!$D$2) -> 0 | K7: =SUMIF(Equipment_Costs!$A:$A,D7,Equipment_Costs!$C:$C) -> 0 | L7: =K7*VLOOKUP(D7,Strategy_Rates!$A:$G,2,FALSE) -> 0 | M7: =(K7+L7)*VLOOKUP(D7,Strategy_Rates!$A:$G,3,FALSE) -> 0 | N7: =K7+L7+M7 -> 0 | O7: =(C7/5000)^VLOOKUP(D7,Strategy_Rates!$A:$G,4,FALSE) -> 0 | P7: =N7*O7 -> 0 | Q7: =(Inputs!$D$6+Inputs!$D$7)/Inputs!$D$5 -> 0 | R7: =Inputs!$D$12*(1000/Inputs!$D$2) -> 0 | S7: =Q7+Inputs!$D$8+Inputs!$D$9+Inputs!$D$10+Inputs!$D$11+R7+Inputs!$D$13+Inputs!$D$14 -> 0 | T7: =Inputs!$D$15+P7*VLOOKUP(D7,Strategy_Rates!$A:$G,5,FALSE)/12 -> 0 | U7: =Inputs!$D$16*(S7*G7+T7) -> 0 | V7: =P7+U7 -> 0 | W7: =I7*G7 -> 0 | X7: =(I7-S7)*G7 -> 0 | Y7: =W7-S7*G7-T7 -> 0 | Z7: =IF(I7>0,(I7-S7)/I7,0) -> 0 | AA7: =IF(I7>S7,T7/(I7-S7),0) -> 0 | AB7: =AA7*1000/Inputs!$D$2 -> 0 | AC7: =AA7*I7 -> 0 | AD7: =IF(Y7>0,V7/(Y7*12),999) -> 0 | AE7: =IF(V7>0,(Y7*36-V7)/V7,0) -> 0 | AF7: =IF(Inputs!$D$17=1,IF(Inputs!$D$19>0,V7*Inputs!$D$18*Inputs!$D$19/(1-(1+Inputs!$D$19)^(-Inputs!$D$20))/12,V7*Inputs!$D$18/Inputs!$D$20/12),0) -> 0 | AG7: =Y7-AF7 -> 0 | AH7: =IF(AF7>0,Y7/AF7,0) -> 0 | AI7: =IF(AND(Z7>=0.35,AD7<=3.5,Y7>0),"GO",IF(AND(Z7>=0.25,Y7>0),"GO conditional",IF(Y7>0,"Risk","NO-GO"))) -> 0
A8: scale_used | B8: Scale-up | C8: 10000 | D8: used | E8: 0.75 | F8: =C8*E8 -> 0 | G8: =F8/12 -> 0 | H8: =G8*1000/Inputs!$D$2 -> 0 | I8: =Inputs!$D$4 -> 0 | J8: =I8/(1000/Inputs!$D$2) -> 0 | K8: =SUMIF(Equipment_Costs!$A:$A,D8,Equipment_Costs!$C:$C) -> 0 | L8: =K8*VLOOKUP(D8,Strategy_Rates!$A:$G,2,FALSE) -> 0 | M8: =(K8+L8)*VLOOKUP(D8,Strategy_Rates!$A:$G,3,FALSE) -> 0 | N8: =K8+L8+M8 -> 0 | O8: =(C8/5000)^VLOOKUP(D8,Strategy_Rates!$A:$G,4,FALSE) -> 0 | P8: =N8*O8 -> 0 | Q8: =(Inputs!$D$6+Inputs!$D$7)/Inputs!$D$5 -> 0 | R8: =Inputs!$D$12*(1000/Inputs!$D$2) -> 0 | S8: =Q8+Inputs!$D$8+Inputs!$D$9+Inputs!$D$10+Inputs!$D$11+R8+Inputs!$D$13+Inputs!$D$14 -> 0 | T8: =Inputs!$D$15+P8*VLOOKUP(D8,Strategy_Rates!$A:$G,5,FALSE)/12 -> 0 | U8: =Inputs!$D$16*(S8*G8+T8) -> 0 | V8: =P8+U8 -> 0 | W8: =I8*G8 -> 0 | X8: =(I8-S8)*G8 -> 0 | Y8: =W8-S8*G8-T8 -> 0 | Z8: =IF(I8>0,(I8-S8)/I8,0) -> 0 | AA8: =IF(I8>S8,T8/(I8-S8),0) -> 0 | AB8: =AA8*1000/Inputs!$D$2 -> 0 | AC8: =AA8*I8 -> 0 | AD8: =IF(Y8>0,V8/(Y8*12),999) -> 0 | AE8: =IF(V8>0,(Y8*36-V8)/V8,0) -> 0 | AF8: =IF(Inputs!$D$17=1,IF(Inputs!$D$19>0,V8*Inputs!$D$18*Inputs!$D$19/(1-(1+Inputs!$D$19)^(-Inputs!$D$20))/12,V8*Inputs!$D$18/Inputs!$D$20/12),0) -> 0 | AG8: =Y8-AF8 -> 0 | AH8: =IF(AF8>0,Y8/AF8,0) -> 0 | AI8: =IF(AND(Z8>=0.35,AD8<=3.5,Y8>0),"GO",IF(AND(Z8>=0.25,Y8>0),"GO conditional",IF(Y8>0,"Risk","NO-GO"))) -> 0
A9: scale_hybrid | B9: Scale-up | C9: 10000 | D9: hybrid | E9: 0.75 | F9: =C9*E9 -> 0 | G9: =F9/12 -> 0 | H9: =G9*1000/Inputs!$D$2 -> 0 | I9: =Inputs!$D$4 -> 0 | J9: =I9/(1000/Inputs!$D$2) -> 0 | K9: =SUMIF(Equipment_Costs!$A:$A,D9,Equipment_Costs!$C:$C) -> 0 | L9: =K9*VLOOKUP(D9,Strategy_Rates!$A:$G,2,FALSE) -> 0 | M9: =(K9+L9)*VLOOKUP(D9,Strategy_Rates!$A:$G,3,FALSE) -> 0 | N9: =K9+L9+M9 -> 0 | O9: =(C9/5000)^VLOOKUP(D9,Strategy_Rates!$A:$G,4,FALSE) -> 0 | P9: =N9*O9 -> 0 | Q9: =(Inputs!$D$6+Inputs!$D$7)/Inputs!$D$5 -> 0 | R9: =Inputs!$D$12*(1000/Inputs!$D$2) -> 0 | S9: =Q9+Inputs!$D$8+Inputs!$D$9+Inputs!$D$10+Inputs!$D$11+R9+Inputs!$D$13+Inputs!$D$14 -> 0 | T9: =Inputs!$D$15+P9*VLOOKUP(D9,Strategy_Rates!$A:$G,5,FALSE)/12 -> 0 | U9: =Inputs!$D$16*(S9*G9+T9) -> 0 | V9: =P9+U9 -> 0 | W9: =I9*G9 -> 0 | X9: =(I9-S9)*G9 -> 0 | Y9: =W9-S9*G9-T9 -> 0 | Z9: =IF(I9>0,(I9-S9)/I9,0) -> 0 | AA9: =IF(I9>S9,T9/(I9-S9),0) -> 0 | AB9: =AA9*1000/Inputs!$D$2 -> 0 | AC9: =AA9*I9 -> 0 | AD9: =IF(Y9>0,V9/(Y9*12),999) -> 0 | AE9: =IF(V9>0,(Y9*36-V9)/V9,0) -> 0 | AF9: =IF(Inputs!$D$17=1,IF(Inputs!$D$19>0,V9*Inputs!$D$18*Inputs!$D$19/(1-(1+Inputs!$D$19)^(-Inputs!$D$20))/12,V9*Inputs!$D$18/Inputs!$D$20/12),0) -> 0 | AG9: =Y9-AF9 -> 0 | AH9: =IF(AF9>0,Y9/AF9,0) -> 0 | AI9: =IF(AND(Z9>=0.35,AD9<=3.5,Y9>0),"GO",IF(AND(Z9>=0.25,Y9>0),"GO conditional",IF(Y9>0,"Risk","NO-GO"))) -> 0
A10: scale_new | B10: Scale-up | C10: 10000 | D10: new | E10: 0.75 | F10: =C10*E10 -> 0 | G10: =F10/12 -> 0 | H10: =G10*1000/Inputs!$D$2 -> 0 | I10: =Inputs!$D$4 -> 0 | J10: =I10/(1000/Inputs!$D$2) -> 0 | K10: =SUMIF(Equipment_Costs!$A:$A,D10,Equipment_Costs!$C:$C) -> 0 | L10: =K10*VLOOKUP(D10,Strategy_Rates!$A:$G,2,FALSE) -> 0 | M10: =(K10+L10)*VLOOKUP(D10,Strategy_Rates!$A:$G,3,FALSE) -> 0 | N10: =K10+L10+M10 -> 0 | O10: =(C10/5000)^VLOOKUP(D10,Strategy_Rates!$A:$G,4,FALSE) -> 0 | P10: =N10*O10 -> 0 | Q10: =(Inputs!$D$6+Inputs!$D$7)/Inputs!$D$5 -> 0 | R10: =Inputs!$D$12*(1000/Inputs!$D$2) -> 0 | S10: =Q10+Inputs!$D$8+Inputs!$D$9+Inputs!$D$10+Inputs!$D$11+R10+Inputs!$D$13+Inputs!$D$14 -> 0 | T10: =Inputs!$D$15+P10*VLOOKUP(D10,Strategy_Rates!$A:$G,5,FALSE)/12 -> 0 | U10: =Inputs!$D$16*(S10*G10+T10) -> 0 | V10: =P10+U10 -> 0 | W10: =I10*G10 -> 0 | X10: =(I10-S10)*G10 -> 0 | Y10: =W10-S10*G10-T10 -> 0 | Z10: =IF(I10>0,(I10-S10)/I10,0) -> 0 | AA10: =IF(I10>S10,T10/(I10-S10),0) -> 0 | AB10: =AA10*1000/Inputs!$D$2 -> 0 | AC10: =AA10*I10 -> 0 | AD10: =IF(Y10>0,V10/(Y10*12),999) -> 0 | AE10: =IF(V10>0,(Y10*36-V10)/V10,0) -> 0 | AF10: =IF(Inputs!$D$17=1,IF(Inputs!$D$19>0,V10*Inputs!$D$18*Inputs!$D$19/(1-(1+Inputs!$D$19)^(-Inputs!$D$20))/12,V10*Inputs!$D$18/Inputs!$D$20/12),0) -> 0 | AG10: =Y10-AF10 -> 0 | AH10: =IF(AF10>0,Y10/AF10,0) -> 0 | AI10: =IF(AND(Z10>=0.35,AD10<=3.5,Y10>0),"GO",IF(AND(Z10>=0.25,Y10>0),"GO conditional",IF(Y10>0,"Risk","NO-GO"))) -> 0
A11: industrial_used | B11: Industrial | C11: 20000 | D11: used | E11: 0.8 | F11: =C11*E11 -> 0 | G11: =F11/12 -> 0 | H11: =G11*1000/Inputs!$D$2 -> 0 | I11: =Inputs!$D$4 -> 0 | J11: =I11/(1000/Inputs!$D$2) -> 0 | K11: =SUMIF(Equipment_Costs!$A:$A,D11,Equipment_Costs!$C:$C) -> 0 | L11: =K11*VLOOKUP(D11,Strategy_Rates!$A:$G,2,FALSE) -> 0 | M11: =(K11+L11)*VLOOKUP(D11,Strategy_Rates!$A:$G,3,FALSE) -> 0 | N11: =K11+L11+M11 -> 0 | O11: =(C11/5000)^VLOOKUP(D11,Strategy_Rates!$A:$G,4,FALSE) -> 0 | P11: =N11*O11 -> 0 | Q11: =(Inputs!$D$6+Inputs!$D$7)/Inputs!$D$5 -> 0 | R11: =Inputs!$D$12*(1000/Inputs!$D$2) -> 0 | S11: =Q11+Inputs!$D$8+Inputs!$D$9+Inputs!$D$10+Inputs!$D$11+R11+Inputs!$D$13+Inputs!$D$14 -> 0 | T11: =Inputs!$D$15+P11*VLOOKUP(D11,Strategy_Rates!$A:$G,5,FALSE)/12 -> 0 | U11: =Inputs!$D$16*(S11*G11+T11) -> 0 | V11: =P11+U11 -> 0 | W11: =I11*G11 -> 0 | X11: =(I11-S11)*G11 -> 0 | Y11: =W11-S11*G11-T11 -> 0 | Z11: =IF(I11>0,(I11-S11)/I11,0) -> 0 | AA11: =IF(I11>S11,T11/(I11-S11),0) -> 0 | AB11: =AA11*1000/Inputs!$D$2 -> 0 | AC11: =AA11*I11 -> 0 | AD11: =IF(Y11>0,V11/(Y11*12),999) -> 0 | AE11: =IF(V11>0,(Y11*36-V11)/V11,0) -> 0 | AF11: =IF(Inputs!$D$17=1,IF(Inputs!$D$19>0,V11*Inputs!$D$18*Inputs!$D$19/(1-(1+Inputs!$D$19)^(-Inputs!$D$20))/12,V11*Inputs!$D$18/Inputs!$D$20/12),0) -> 0 | AG11: =Y11-AF11 -> 0 | AH11: =IF(AF11>0,Y11/AF11,0) -> 0 | AI11: =IF(AND(Z11>=0.35,AD11<=3.5,Y11>0),"GO",IF(AND(Z11>=0.25,Y11>0),"GO conditional",IF(Y11>0,"Risk","NO-GO"))) -> 0
A12: industrial_hybrid | B12: Industrial | C12: 20000 | D12: hybrid | E12: 0.8 | F12: =C12*E12 -> 0 | G12: =F12/12 -> 0 | H12: =G12*1000/Inputs!$D$2 -> 0 | I12: =Inputs!$D$4 -> 0 | J12: =I12/(1000/Inputs!$D$2) -> 0 | K12: =SUMIF(Equipment_Costs!$A:$A,D12,Equipment_Costs!$C:$C) -> 0 | L12: =K12*VLOOKUP(D12,Strategy_Rates!$A:$G,2,FALSE) -> 0 | M12: =(K12+L12)*VLOOKUP(D12,Strategy_Rates!$A:$G,3,FALSE) -> 0 | N12: =K12+L12+M12 -> 0 | O12: =(C12/5000)^VLOOKUP(D12,Strategy_Rates!$A:$G,4,FALSE) -> 0 | P12: =N12*O12 -> 0 | Q12: =(Inputs!$D$6+Inputs!$D$7)/Inputs!$D$5 -> 0 | R12: =Inputs!$D$12*(1000/Inputs!$D$2) -> 0 | S12: =Q12+Inputs!$D$8+Inputs!$D$9+Inputs!$D$10+Inputs!$D$11+R12+Inputs!$D$13+Inputs!$D$14 -> 0 | T12: =Inputs!$D$15+P12*VLOOKUP(D12,Strategy_Rates!$A:$G,5,FALSE)/12 -> 0 | U12: =Inputs!$D$16*(S12*G12+T12) -> 0 | V12: =P12+U12 -> 0 | W12: =I12*G12 -> 0 | X12: =(I12-S12)*G12 -> 0 | Y12: =W12-S12*G12-T12 -> 0 | Z12: =IF(I12>0,(I12-S12)/I12,0) -> 0 | AA12: =IF(I12>S12,T12/(I12-S12),0) -> 0 | AB12: =AA12*1000/Inputs!$D$2 -> 0 | AC12: =AA12*I12 -> 0 | AD12: =IF(Y12>0,V12/(Y12*12),999) -> 0 | AE12: =IF(V12>0,(Y12*36-V12)/V12,0) -> 0 | AF12: =IF(Inputs!$D$17=1,IF(Inputs!$D$19>0,V12*Inputs!$D$18*Inputs!$D$19/(1-(1+Inputs!$D$19)^(-Inputs!$D$20))/12,V12*Inputs!$D$18/Inputs!$D$20/12),0) -> 0 | AG12: =Y12-AF12 -> 0 | AH12: =IF(AF12>0,Y12/AF12,0) -> 0 | AI12: =IF(AND(Z12>=0.35,AD12<=3.5,Y12>0),"GO",IF(AND(Z12>=0.25,Y12>0),"GO conditional",IF(Y12>0,"Risk","NO-GO"))) -> 0
A13: industrial_new | B13: Industrial | C13: 20000 | D13: new | E13: 0.8 | F13: =C13*E13 -> 0 | G13: =F13/12 -> 0 | H13: =G13*1000/Inputs!$D$2 -> 0 | I13: =Inputs!$D$4 -> 0 | J13: =I13/(1000/Inputs!$D$2) -> 0 | K13: =SUMIF(Equipment_Costs!$A:$A,D13,Equipment_Costs!$C:$C) -> 0 | L13: =K13*VLOOKUP(D13,Strategy_Rates!$A:$G,2,FALSE) -> 0 | M13: =(K13+L13)*VLOOKUP(D13,Strategy_Rates!$A:$G,3,FALSE) -> 0 | N13: =K13+L13+M13 -> 0 | O13: =(C13/5000)^VLOOKUP(D13,Strategy_Rates!$A:$G,4,FALSE) -> 0 | P13: =N13*O13 -> 0 | Q13: =(Inputs!$D$6+Inputs!$D$7)/Inputs!$D$5 -> 0 | R13: =Inputs!$D$12*(1000/Inputs!$D$2) -> 0 | S13: =Q13+Inputs!$D$8+Inputs!$D$9+Inputs!$D$10+Inputs!$D$11+R13+Inputs!$D$13+Inputs!$D$14 -> 0 | T13: =Inputs!$D$15+P13*VLOOKUP(D13,Strategy_Rates!$A:$G,5,FALSE)/12 -> 0 | U13: =Inputs!$D$16*(S13*G13+T13) -> 0 | V13: =P13+U13 -> 0 | W13: =I13*G13 -> 0 | X13: =(I13-S13)*G13 -> 0 | Y13: =W13-S13*G13-T13 -> 0 | Z13: =IF(I13>0,(I13-S13)/I13,0) -> 0 | AA13: =IF(I13>S13,T13/(I13-S13),0) -> 0 | AB13: =AA13*1000/Inputs!$D$2 -> 0 | AC13: =AA13*I13 -> 0 | AD13: =IF(Y13>0,V13/(Y13*12),999) -> 0 | AE13: =IF(V13>0,(Y13*36-V13)/V13,0) -> 0 | AF13: =IF(Inputs!$D$17=1,IF(Inputs!$D$19>0,V13*Inputs!$D$18*Inputs!$D$19/(1-(1+Inputs!$D$19)^(-Inputs!$D$20))/12,V13*Inputs!$D$18/Inputs!$D$20/12),0) -> 0 | AG13: =Y13-AF13 -> 0 | AH13: =IF(AF13>0,Y13/AF13,0) -> 0 | AI13: =IF(AND(Z13>=0.35,AD13<=3.5,Y13>0),"GO",IF(AND(Z13>=0.25,Y13>0),"GO conditional",IF(Y13>0,"Risk","NO-GO"))) -> 0

Sheet Sensitivity
A1: Driver | B1: Downside | C1: Base | D1: Upside | E1: Unit | F1: Notes
A2: selling_price_eur_per_ton | B2: 105 | C2: 120 | D2: 135 | E2: EUR/t | F2: Commercial pricing sensitivity
A3: process_yield | B3: 0.68 | C3: 0.75 | D3: 0.82 | E3: ratio | F3: Technical yield sensitivity
A4: utilization_pct | B4: 0.55 | C4: 0.7 | D4: 0.85 | E4: ratio | F4: Market demand and capacity absorption
A5: capex_multiplier | B5: 1.2 | C5: 1 | D5: 0.9 | E5: ratio | F5: Quote and installation uncertainty
A6: raw_material_cost_eur_per_finished_t | B6: 18 | C6: 16 | D6: 12 | E6: EUR/t | F6: Extraction plus quarry-to-plant transport after yield
A7: fixed_opex_eur_per_month | B7: 12000 | C7: 8000 | D7: 6000 | E7: EUR/month | F7: Overhead discipline sensitivity

Sheet Decision_Summary
A1: Metric | B1: Value | C1: Notes
A2: Recommended working case | B2: start_hybrid | C2: Balanced phase 1 scenario for discussion
A3: Recommended capacity | B3: =INDEX(Scenario_Matrix!$C:$C,MATCH("start_hybrid",Scenario_Matrix!$A:$A,0)) -> 0 | C3: t/year
A4: Recommended strategy | B4: =INDEX(Scenario_Matrix!$D:$D,MATCH("start_hybrid",Scenario_Matrix!$A:$A,0)) -> 0 | C4: equipment strategy
A5: Recommended EBITDA/month | B5: =INDEX(Scenario_Matrix!$Y:$Y,MATCH("start_hybrid",Scenario_Matrix!$A:$A,0)) -> 0 | C5: EUR/month before debt
A6: Recommended payback years | B6: =INDEX(Scenario_Matrix!$AD:$AD,MATCH("start_hybrid",Scenario_Matrix!$A:$A,0)) -> 0 | C6: years before debt
A7: Recommended ROI 3y | B7: =INDEX(Scenario_Matrix!$AE:$AE,MATCH("start_hybrid",Scenario_Matrix!$A:$A,0)) -> 0 | C7: before debt
A8: Best EBITDA scenario | B8: =INDEX(Scenario_Matrix!$A:$A,MATCH(MAX(Scenario_Matrix!$Y:$Y),Scenario_Matrix!$Y:$Y,0)) -> 0 | C8: highest monthly EBITDA
A9: Best payback scenario | B9: =INDEX(Scenario_Matrix!$A:$A,MATCH(MIN(Scenario_Matrix!$AD:$AD),Scenario_Matrix!$AD:$AD,0)) -> 0 | C9: lowest payback years
A10: Critical rule | B10: Do not buy equipment before lab quality and buyer validation | C10: Decision gate
